gmtk/__init__.py
gmtk-0.0.1.dist-info/LICENSE
gmtk-0.0.1.dist-info/METADATA
gmtk-0.0.1.dist-info/WHEEL
gmtk-0.0.1.dist-info/top_level.txt
gmtk-0.0.1.dist-info/RECORD
