Metadata-Version: 2.1
Name: gmtk
Version: 0.0.1
Summary: Python interface for handling Graphical Models Toolkit markup
Home-page: https://github.com/hoffmangroup/gmtk
Author: Michael Hoffman
Author-email: michael.hoffman@utoronto.ca
License: UNKNOWN
Platform: UNKNOWN
Classifier: Programming Language :: Python
Classifier: License :: OSI Approved :: GNU General Public License v2 (GPLv2)
